annofabapi/__init__.py
annofabapi/__version__.py
annofabapi/_utils.py
annofabapi/api.py
annofabapi/api2.py
annofabapi/credentials.py
annofabapi/dataclass/__init__.py
annofabapi/dataclass/annotation.py
annofabapi/dataclass/annotation_specs.py
annofabapi/dataclass/comment.py
annofabapi/dataclass/input.py
annofabapi/dataclass/job.py
annofabapi/dataclass/organization.py
annofabapi/dataclass/organization_member.py
annofabapi/dataclass/project.py
annofabapi/dataclass/project_member.py
annofabapi/dataclass/supplementary.py
annofabapi/dataclass/task.py
annofabapi/exceptions.py
annofabapi/generated_api.py
annofabapi/generated_api2.py
annofabapi/models.py
annofabapi/parser.py
annofabapi/plugin.py
annofabapi/py.typed
annofabapi/pydantic_models/__init__.py
annofabapi/pydantic_models/accept_organization_invitation_request.py
annofabapi/pydantic_models/account.py
annofabapi/pydantic_models/account_worktime_statistics.py
annofabapi/pydantic_models/action_required.py
annofabapi/pydantic_models/additional_data_default_type.py
annofabapi/pydantic_models/additional_data_definition_type.py
annofabapi/pydantic_models/additional_data_definition_v1.py
annofabapi/pydantic_models/additional_data_definition_v1_choices_inner.py
annofabapi/pydantic_models/additional_data_definition_v2.py
annofabapi/pydantic_models/additional_data_restriction.py
annofabapi/pydantic_models/additional_data_restriction_condition.py
annofabapi/pydantic_models/additional_data_restriction_condition_can_input.py
annofabapi/pydantic_models/additional_data_restriction_condition_equals.py
annofabapi/pydantic_models/additional_data_restriction_condition_has_label.py
annofabapi/pydantic_models/additional_data_restriction_condition_imply.py
annofabapi/pydantic_models/additional_data_restriction_condition_matches.py
annofabapi/pydantic_models/additional_data_restriction_condition_not_equals.py
annofabapi/pydantic_models/additional_data_restriction_condition_not_matches.py
annofabapi/pydantic_models/additional_data_v1.py
annofabapi-2.1.0.dist-info/LICENSE
annofabapi-2.1.0.dist-info/METADATA
annofabapi-2.1.0.dist-info/WHEEL
annofabapi-2.1.0.dist-info/RECORD
