Metadata-Version: 2.1
Name: annofabapi
Version: 2.1.0
Summary: Python Clinet Library of Annofab WebAPI (https://annofab.com/docs/api/)
Home-page: https://github.com/kurusugawa-computer/annofab-api-python-client
License: MIT
Keywords: annofab,api
Author: Kurusugawa Computer Inc.
Requires-Python: >=3.9,<4.0
Classifier: Development Status :: 4 - Beta
Classifier: Intended Audience :: Developers
Classifier: License :: OSI Approved :: MIT License
Classifier: Operating System :: OS Independent
Classifier: Programming Language :: Python :: 3
Classifier: Programming Language :: Python :: 3.9
Classifier: Programming Language :: Python :: 3.10
Classifier: Programming Language :: Python :: 3.11
Classifier: Programming Language :: Python :: 3.12
Classifier: Programming Language :: Python :: 3.13
Classifier: Topic :: Utilities
Provides-Extra: segmentation
Requires-Dist: backoff
Requires-Dist: dataclasses-json
Requires-Dist: more-itertools
Requires-Dist: numpy ; extra == "segmentation"
Requires-Dist: pillow ; extra == "segmentation"
Requires-Dist: pydantic (>=2,<3)
Requires-Dist: python-dateutil
Requires-Dist: requests
Project-URL: Repository, https://github.com/kurusugawa-computer/annofab-api-python-client
